[
	{
		"id": "5001",
		"name": "Bioderm Coolness 135g",
		"price": 50.00,
		"category": "general-merchandise",
		"subcategory": "Bathing Cleaning Materials",
		"brand": "Bioderm",
		"tags": ["soap","bathing","bioderm"],
		"stock": 5,
		"description": "Bioderm Coolness 135g",
		"image_url": "images/general-merch/bathing/bioderm-coolness-135g.jpg",
		"image_webp": "images/general-merch/bathing/bioderm-coolness-135g.webp"
	},
	{
		"id": "5002",
		"name": "Bioderm Coolness 60g",
		"price": 20.00,
		"category": "general-merchandise",
		"subcategory": "Bathing Cleaning Materials",
		"brand": "Bioderm",
		"tags": ["soap","bathing","bioderm","travel"],
		"stock": 10,
		"description": "Bioderm Coolness 60g",
		"image_url": "images/general-merch/bathing/bioderm-coolness-60g.jpg",
		"image_webp": "images/general-merch/bathing/bioderm-coolness-60g.webp"
	},
	{
		"id": "5003",
		"name": "Bioderm Freshen 135g",
		"price": 50.00,
		"category": "general-merchandise",
		"subcategory": "Bathing Cleaning Materials",
		"brand": "Bioderm",
		"tags": ["soap","bathing","bioderm"],
		"stock": 5,
		"description": "Bioderm Freshen 135g",
		"image_url": "images/general-merch/bathing/bioderm-freshen-135g.jpg",
		"image_webp": "images/general-merch/bathing/bioderm-freshen-135g.webp"
	},
	{
		"id": "5004",
		"name": "Bioderm Freshen 60g",
		"price": 20.00,
		"category": "general-merchandise",
		"subcategory": "Bathing Cleaning Materials",
		"brand": "Bioderm",
		"tags": ["soap","bathing","bioderm","travel"],
		"stock": 10,
		"description": "Bioderm Freshen 60g",
		"image_url": "images/general-merch/bathing/bioderm-freshen-60g.jpg",
		"image_webp": "images/general-merch/bathing/bioderm-freshen-60g.webp"
	},
	{
		"id": "5005",
		"name": "Bioderm Pink Bloom 135g",
		"price": 50.00,
		"category": "general-merchandise",
		"subcategory": "Bathing Cleaning Materials",
		"brand": "Bioderm",
		"tags": ["soap","bathing","bioderm","pink"],
		"stock": 5,
		"description": "Bioderm Pink Bloom 135g",
		"image_url": "images/general-merch/bathing/bioderm-pinkbloom-135g.jpg",
		"image_webp": "images/general-merch/bathing/bioderm-pinkbloom-135g.webp"
	},
	{
		"id": "5006",
		"name": "Bioderm Pink Bloom 60g",
		"price": 20.00,
		"category": "general-merchandise",
		"subcategory": "Bathing Cleaning Materials",
		"brand": "Bioderm",
		"tags": ["soap","bathing","bioderm","pink","travel"],
		"stock": 10,
		"description": "Bioderm Pink Bloom 60g",
		"image_url": "images/general-merch/bathing/bioderm-pinkbloom-60g.jpg",
		"image_webp": "images/general-merch/bathing/bioderm-pinkbloom-60g.webp"
	},
	{
		"id": "5007",
		"name": "Safeguard White 85g",
		"price": 50.00,
		"category": "general-merchandise",
		"subcategory": "Bathing Cleaning Materials",
		"brand": "Safeguard",
		"tags": ["soap","safeguard","bathing"],
		"stock": 5,
		"description": "Safeguard White 85g",
		"image_url": "images/general-merch/bathing/safeguard-white-85g.jpg",
		"image_webp": "images/general-merch/bathing/safeguard-white-85g.webp"
	},
	{
		"id": "5008",
		"name": "Safeguard Fresh Green 85g",
		"price": 50.00,
		"category": "general-merchandise",
		"subcategory": "Bathing Cleaning Materials",
		"brand": "Safeguard",
		"tags": ["soap","safeguard","fresh","bathing"],
		"stock": 5,
		"description": "Safeguard Fresh Green 85g",
		"image_url": "images/general-merch/bathing/safeguard-freshgreen-85g.jpg",
		"image_webp": "images/general-merch/bathing/safeguard-freshgreen-85g.webp"
	},
	{
		"id": "5009",
		"name": "Safeguard Fresh Green 60g",
		"price": 20.00,
		"category": "general-merchandise",
		"subcategory": "Bathing Cleaning Materials",
		"brand": "Safeguard",
		"tags": ["soap","safeguard","fresh","travel"],
		"stock": 10,
		"description": "Safeguard Fresh Green 60g",
		"image_url": "images/general-merch/bathing/safeguard-freshgreen-60g.jpg",
		"image_webp": "images/general-merch/bathing/safeguard-freshgreen-60g.webp"
	},
	{
		"id": "5010",
		"name": "Safeguard Floral Pink 85g",
		"price": 50.00,
		"category": "general-merchandise",
		"subcategory": "Bathing Cleaning Materials",
		"brand": "Safeguard",
		"tags": ["soap","safeguard","floral","bathing"],
		"stock": 5,
		"description": "Safeguard Floral Pink 85g",
		"image_url": "images/general-merch/bathing/safeguard-floralpink-85g.jpg",
		"image_webp": "images/general-merch/bathing/safeguard-floralpink-85g.webp"
	},
	{
		"id": "5011",
		"name": "Safeguard Floral Pink 60g",
		"price": 20.00,
		"category": "general-merchandise",
		"subcategory": "Bathing Cleaning Materials",
		"brand": "Safeguard",
		"tags": ["soap","safeguard","floral","travel"],
		"stock": 10,
		"description": "Safeguard Floral Pink 60g",
		"image_url": "images/general-merch/bathing/safeguard-floralpink-60g.jpg",
		"image_webp": "images/general-merch/bathing/safeguard-floralpink-60g.webp"
	},
	{
		"id": "5012",
		"name": "Safeguard Extra Cool 60g",
		"price": 20.00,
		"category": "general-merchandise",
		"subcategory": "Bathing Cleaning Materials",
		"brand": "Safeguard",
		"tags": ["soap","safeguard","bathing","cool"],
		"stock": 10,
		"description": "Safeguard Extra Cool 60g",
		"image_url": "images/general-merch/bathing/safeguard-extracool-60g.jpg",
		"image_webp": "images/general-merch/bathing/safeguard-extracool-60g.webp"
	},
	{
		"id": "5013",
		"name": "Sunsilk Smooth and Manageable Sachet",
		"price": 12.00,
		"category": "general-merchandise",
		"subcategory": "Bathing Cleaning Materials",
		"brand": "Sunsilk",
		"tags": ["hair","sachet","sunsilk"],
		"stock": 20,
		"description": "Sunsilk Smooth and Manageable Sachet",
		"image_url": "images/general-merch/bathing/sunsilk-pink-sachet.jpg",
		"image_webp": "images/general-merch/bathing/sunsilk-pink-sachet.webp"
	},
	{
		"id": "5014",
		"name": "Pantene Hair Fall Control Sachet",
		"price": 12.00,
		"category": "general-merchandise",
		"subcategory": "Bathing Cleaning Materials",
		"brand": "Pantene",
		"tags": ["hair","sachet","pantene"],
		"stock": 20,
		"description": "Pantene Hair Fall Control Sachet",
		"image_url": "images/general-merch/bathing/pantene-sachet.jpg",
		"image_webp": "images/general-merch/bathing/pantene-sachet.webp"
	},
	{
		"id": "5015",
		"name": "Palmolive Intensive Moisture Sachet",
		"price": 12.00,
		"category": "general-merchandise",
		"subcategory": "Bathing Cleaning Materials",
		"brand": "Palmolive",
		"tags": ["hair","sachet","palmolive"],
		"stock": 20,
		"description": "Palmolive Intensive Moisture Sachet",
		"image_url": "images/general-merch/bathing/palmolive-sachet.jpg",
		"image_webp": "images/general-merch/bathing/palmolive-sachet.webp"
	},
	{
		"id": "5016",
		"name": "Head and Shoulders Cool Menthol Sachet",
		"price": 12.00,
		"category": "general-merchandise",
		"subcategory": "Bathing Cleaning Materials",
		"brand": "Head & Shoulders",
		"tags": ["hair","sachet","head-and-shoulders","menthol"],
		"stock": 20,
		"description": "Head and Shoulders Cool Menthol Sachet",
		"image_url": "images/general-merch/bathing/headnshoulders-menthol-sachet.jpg",
		"image_webp": "images/general-merch/bathing/headnshoulders-menthol-sachet.webp"
	},
	{
		"id": "5017",
		"name": "Creamsilk Standout Straight Sachet",
		"price": 15.00,
		"category": "general-merchandise",
		"subcategory": "Bathing Cleaning Materials",
		"brand": "Creamsilk",
		"tags": ["hair","sachet","creamsilk"],
		"stock": 20,
		"description": "Creamsilk Standout Straight Sachet",
		"image_url": "images/general-merch/bathing/creamsilk-sachet.jpg",
		"image_webp": "images/general-merch/bathing/creamsilk-sachet.webp"
	},
	{
		"id": "5018",
		"name": "Clear Anti Dandruff Women Sachet",
		"price": 12.00,
		"category": "general-merchandise",
		"subcategory": "Bathing Cleaning Materials",
		"brand": "Clear",
		"tags": ["hair","sachet","clear","anti-dandruff","women"],
		"stock": 20,
		"description": "Clear Anti Dandruff Women Sachet",
		"image_url": "images/general-merch/bathing/clear-women-sachet.jpg",
		"image_webp": "images/general-merch/bathing/clear-women-sachet.webp"
	},
	{
		"id": "5019",
		"name": "Clear Anti Dandruff Men Sachet",
		"price": 12.00,
		"category": "general-merchandise",
		"subcategory": "Bathing Cleaning Materials",
		"brand": "Clear",
		"tags": ["hair","sachet","clear","anti-dandruff","men"],
		"stock": 20,
		"description": "Clear Anti Dandruff Men Sachet",
		"image_url": "images/general-merch/bathing/clear-menthol-men-sachet.jpg",
		"image_webp": "images/general-merch/bathing/clear-menthol-men-sachet.webp"
	}
,
	{
		"id": "5020",
		"name": "Zonrox Original 500ml",
		"price": 100.00,
		"category": "general-merchandise",
		"subcategory": "Laundry Cleaning Materials",
		"brand": "Zonrox",
		"tags": ["bleach","zonrox","laundry"],
		"stock": 5,
		"description": "Zonrox Original 500ml",
		"image_url": "images/general-merch/laundry/zonrox-orig-500ml.jpg",
		"image_webp": "images/general-merch/laundry/zonrox-orig-500ml.webp"
	},
	{
		"id": "5021",
		"name": "Zonrox Original 250ml",
		"price": 70.00,
		"category": "general-merchandise",
		"subcategory": "Laundry Cleaning Materials",
		"brand": "Zonrox",
		"tags": ["bleach","zonrox","laundry"],
		"stock": 10,
		"description": "Zonrox Original 250ml",
		"image_url": "images/general-merch/laundry/zonrox-orig-250ml.jpg",
		"image_webp": "images/general-merch/laundry/zonrox-orig-250ml.webp"
	},
	{
		"id": "5022",
		"name": "Zonrox Original 100ml",
		"price": 40.00,
		"category": "general-merchandise",
		"subcategory": "Laundry Cleaning Materials",
		"brand": "Zonrox",
		"tags": ["bleach","zonrox","laundry"],
		"stock": 10,
		"description": "Zonrox Original 100ml",
		"image_url": "images/general-merch/laundry/zonrox-orig-100ml.jpg",
		"image_webp": "images/general-merch/laundry/zonrox-orig-100ml.webp"
	},
	{
		"id": "5023",
		"name": "Zonrox Color Safe 500ml",
		"price": 100.00,
		"category": "general-merchandise",
		"subcategory": "Laundry Cleaning Materials",
		"brand": "Zonrox",
		"tags": ["bleach","zonrox","color-safe","laundry"],
		"stock": 5,
		"description": "Zonrox Color Safe 500ml",
		"image_url": "images/general-merch/laundry/zonrox-colorsafe-500ml.jpg",
		"image_webp": "images/general-merch/laundry/zonrox-colorsafe-500ml.webp"
	},
	{
		"id": "5024",
		"name": "Zonrox Color Safe 225ml",
		"price": 70.00,
		"category": "general-merchandise",
		"subcategory": "Laundry Cleaning Materials",
		"brand": "Zonrox",
		"tags": ["bleach","zonrox","color-safe","laundry"],
		"stock": 10,
		"description": "Zonrox Color Safe 225ml",
		"image_url": "images/general-merch/laundry/zonrox-colorsafe-225ml.jpg",
		"image_webp": "images/general-merch/laundry/zonrox-colorsafe-225ml.webp"
	},
	{
		"id": "5025",
		"name": "Zonrox Color Safe 95ml",
		"price": 50.00,
		"category": "general-merchandise",
		"subcategory": "Laundry Cleaning Materials",
		"brand": "Zonrox",
		"tags": ["bleach","zonrox","color-safe","laundry"],
		"stock": 10,
		"description": "Zonrox Color Safe 95ml",
		"image_url": "images/general-merch/laundry/zonrox-colorsafe-95ml.jpg",
		"image_webp": "images/general-merch/laundry/zonrox-colorsafe-95ml.webp"
	},
	{
		"id": "5026",
		"name": "Wings Summer Sunshine 70g",
		"price": 15.00,
		"category": "general-merchandise",
		"subcategory": "Laundry Cleaning Materials",
		"brand": "Wings",
		"tags": ["detergent","wings","laundry","sachet"],
		"stock": 20,
		"description": "Wings Summer Sunshine 70g",
		"image_url": "images/general-merch/laundry/wings-summersunshine-70g.jpg",
		"image_webp": "images/general-merch/laundry/wings-summersunshine-70g.webp"
	},
	{
		"id": "5027",
		"name": "Wings Floral Fresh 70g",
		"price": 15.00,
		"category": "general-merchandise",
		"subcategory": "Laundry Cleaning Materials",
		"brand": "Wings",
		"tags": ["detergent","wings","laundry","sachet"],
		"stock": 20,
		"description": "Wings Floral Fresh 70g",
		"image_url": "images/general-merch/laundry/wings-floralfresh-70g.jpg",
		"image_webp": "images/general-merch/laundry/wings-floralfresh-70g.webp"
	},
	{
		"id": "5028",
		"name": "Wings Calamansi 70g",
		"price": 15.00,
		"category": "general-merchandise",
		"subcategory": "Laundry Cleaning Materials",
		"brand": "Wings",
		"tags": ["detergent","wings","laundry","sachet"],
		"stock": 20,
		"description": "Wings Calamansi 70g",
		"image_url": "images/general-merch/laundry/wings-calamansi-70g.jpg",
		"image_webp": "images/general-merch/laundry/wings-calamansi-70g.webp"
	},
	{
		"id": "5029",
		"name": "Surf Sun Fresh 65g",
		"price": 12.00,
		"category": "general-merchandise",
		"subcategory": "Laundry Cleaning Materials",
		"brand": "Surf",
		"tags": ["detergent","surf","laundry","sachet"],
		"stock": 20,
		"description": "Surf Sun Fresh 65g",
		"image_url": "images/general-merch/laundry/surf-sunfresh-65g.jpg",
		"image_webp": "images/general-merch/laundry/surf-sunfresh-65g.webp"
	}
,
	{
		"id": "5030",
		"name": "Surf Rose Fresh 65g",
		"price": 12.00,
		"category": "general-merchandise",
		"subcategory": "Laundry Cleaning Materials",
		"brand": "Surf",
		"tags": ["detergent","surf","laundry","sachet","rose"],
		"stock": 20,
		"description": "Surf Rose Fresh 65g",
		"image_url": "images/general-merch/laundry/surf-rosefresh-65g.jpg",
		"image_webp": "images/general-merch/laundry/surf-rosefresh-65g.webp"
	},
	{
		"id": "5031",
		"name": "Surf Kalamansi 65g",
		"price": 12.00,
		"category": "general-merchandise",
		"subcategory": "Laundry Cleaning Materials",
		"brand": "Surf",
		"tags": ["detergent","surf","laundry","sachet","kalamansi"],
		"stock": 20,
		"description": "Surf Kalamansi 65g",
		"image_url": "images/general-merch/laundry/surf-kalamansi-65g.jpg",
		"image_webp": "images/general-merch/laundry/surf-kalamansi-65g.webp"
	},
	{
		"id": "5032",
		"name": "Calla Rose Garden 45g",
		"price": 15.00,
		"category": "general-merchandise",
		"subcategory": "Laundry Cleaning Materials",
		"brand": "Calla",
		"tags": ["detergent","calla","laundry","sachet","rose"],
		"stock": 20,
		"description": "Calla Rose Garden 45g",
		"image_url": "images/general-merch/laundry/calla-rosegarden-45g.jpg",
		"image_webp": "images/general-merch/laundry/calla-rosegarden-45g.webp"
	},
	{
		"id": "5033",
		"name": "Calla Kalamansi 45g",
		"price": 15.00,
		"category": "general-merchandise",
		"subcategory": "Laundry Cleaning Materials",
		"brand": "Calla",
		"tags": ["detergent","calla","laundry","sachet","kalamansi"],
		"stock": 20,
		"description": "Calla Kalamansi 45g",
		"image_url": "images/general-merch/laundry/calla-kalamansi-45g.jpg",
		"image_webp": "images/general-merch/laundry/calla-kalamansi-45g.webp"
	},
	{
		"id": "5034",
		"name": "Calla Floral Fresh 45g",
		"price": 15.00,
		"category": "general-merchandise",
		"subcategory": "Laundry Cleaning Materials",
		"brand": "Calla",
		"tags": ["detergent","calla","laundry","sachet","floral"],
		"stock": 20,
		"description": "Calla Floral Fresh 45g",
		"image_url": "images/general-merch/laundry/calla-floralfresh-45g.jpg",
		"image_webp": "images/general-merch/laundry/calla-floralfresh-45g.webp"
	},
	{
		"id": "5035",
		"name": "Ariel with Downy 64g",
		"price": 20.00,
		"category": "general-merchandise",
		"subcategory": "Laundry Cleaning Materials",
		"brand": "Ariel",
		"tags": ["detergent","ariel","downy","laundry"],
		"stock": 20,
		"description": "Ariel with Downy 64g",
		"image_url": "images/general-merch/laundry/ariel-withdowny-64g.jpg",
		"image_webp": "images/general-merch/laundry/ariel-withdowny-64g.webp"
	},
	{
		"id": "5036",
		"name": "Tide Original 69g",
		"price": 20.00,
		"category": "general-merchandise",
		"subcategory": "Laundry Cleaning Materials",
		"brand": "Tide",
		"tags": ["detergent","tide","laundry"],
		"stock": 20,
		"description": "Tide Original 69g",
		"image_url": "images/general-merch/laundry/tide-powder-69g.jpg",
		"image_webp": "images/general-merch/laundry/tide-powder-69g.webp"
	},
	{
		"id": "5037",
		"name": "Downy Antibac 26ml",
		"price": 30.00,
		"category": "general-merchandise",
		"subcategory": "Laundry Cleaning Materials",
		"brand": "Downy",
		"tags": ["downy","fabric-softener","antibac","laundry"],
		"stock": 20,
		"description": "Downy Antibac 26ml",
		"image_url": "images/general-merch/laundry/downy-antibac-26ml.jpg",
		"image_webp": "images/general-merch/laundry/downy-antibac-26ml.webp"
	},
	{
		"id": "5038",
		"name": "Downy Garden Bloom 26ml",
		"price": 30.00,
		"category": "general-merchandise",
		"subcategory": "Laundry Cleaning Materials",
		"brand": "Downy",
		"tags": ["downy","fabric-softener","garden-bloom","laundry"],
		"stock": 20,
		"description": "Downy Garden Bloom 26ml",
		"image_url": "images/general-merch/laundry/downy-gardenbloom-26ml.jpg",
		"image_webp": "images/general-merch/laundry/downy-gardenbloom-26ml.webp"
	},
	{
		"id": "5039",
		"name": "Downy Mystique Perfume 33ml",
		"price": 30.00,
		"category": "general-merchandise",
		"subcategory": "Laundry Cleaning Materials",
		"brand": "Downy",
		"tags": ["downy","fabric-softener","perfume","laundry"],
		"stock": 20,
		"description": "Downy Mystique Perfume 33ml",
		"image_url": "images/general-merch/laundry/downy-mystique-33ml.jpg",
		"image_webp": "images/general-merch/laundry/downy-mystique-33ml.webp"
	}
	,
	{
		"id": "5040",
		"name": "Downy Sunrise Fresh 26ml",
		"price": 30.00,
		"category": "general-merchandise",
		"subcategory": "Laundry Cleaning Materials",
		"brand": "Downy",
		"tags": ["downy","fabric-softener","sunrise","laundry"],
		"stock": 20,
		"description": "Downy Sunrise Fresh 26ml",
		"image_url": "images/general-merch/laundry/downy-sunrisefresh-26ml.jpg",
		"image_webp": "images/general-merch/laundry/downy-sunrisefresh-26ml.webp"
	},
	{
		"id": "5041",
		"name": "Surf Bar Blossom Fresh 120g",
		"price": 20.00,
		"category": "general-merchandise",
		"subcategory": "Laundry Cleaning Materials",
		"brand": "Surf",
		"tags": ["detergent","surf","bar","blossom"],
		"stock": 10,
		"description": "Surf Bar Blossom Fresh 120g",
		"image_url": "images/general-merch/laundry/surfbar-blossomfresh-120g.jpg",
		"image_webp": "images/general-merch/laundry/surfbar-blossomfresh-120g.webp"
	},
	{
		"id": "5042",
		"name": "Surf Bar Kalamansi 120g",
		"price": 20.00,
		"category": "general-merchandise",
		"subcategory": "Laundry Cleaning Materials",
		"brand": "Surf",
		"tags": ["detergent","surf","bar","kalamansi"],
		"stock": 10,
		"description": "Surf Bar Kalamansi 120g",
		"image_url": "images/general-merch/laundry/surfbar-kalamansi-120g.jpg",
		"image_webp": "images/general-merch/laundry/surfbar-kalamansi-120g.webp"
	},
	{
		"id": "5043",
		"name": "Surf Bar Sun Fresh 120g",
		"price": 20.00,
		"category": "general-merchandise",
		"subcategory": "Laundry Cleaning Materials",
		"brand": "Surf",
		"tags": ["detergent","surf","bar","sunfresh"],
		"stock": 10,
		"description": "Surf Bar Sun Fresh 120g",
		"image_url": "images/general-merch/laundry/surfbar-sunfresh-120g.jpg",
		"image_webp": "images/general-merch/laundry/surfbar-sunfresh-120g.webp"
	},
	{
		"id": "5044",
		"name": "Tide Taba Bar Original 125g",
		"price": 30.00,
		"category": "general-merchandise",
		"subcategory": "Laundry Cleaning Materials",
		"brand": "Tide",
		"tags": ["detergent","tide","bar","taba"],
		"stock": 10,
		"description": "Tide Taba Bar Original 125g",
		"image_url": "images/general-merch/laundry/tidebar-tabaorigscent-125g.jpg",
		"image_webp": "images/general-merch/laundry/tidebar-tabaorigscent-125g.webp"
	}

,
	{
		"id": "5045",
		"name": "Joy Calamansi 250ml",
		"price": 100.00,
		"category": "general-merchandise",
		"subcategory": "Kitchen Cleaning Materials",
		"brand": "Joy",
		"tags": ["dishwashing","joy","calamansi","kitchen"],
		"stock": 5,
		"description": "Joy Calamansi 250ml",
		"image_url": "images/general-merch/kitchen/joy-calamansi-250ml.jpg",
		"image_webp": "images/general-merch/kitchen/joy-calamansi-250ml.webp"
	},
	{
		"id": "5046",
		"name": "Joy Calamansi 40ml",
		"price": 20.00,
		"category": "general-merchandise",
		"subcategory": "Kitchen Cleaning Materials",
		"brand": "Joy",
		"tags": ["dishwashing","joy","calamansi","sachet","kitchen"],
		"stock": 10,
		"description": "Joy Calamansi 40ml",
		"image_url": "images/general-merch/kitchen/joy-calamansi-40ml.jpg",
		"image_webp": "images/general-merch/kitchen/joy-calamansi-40ml.webp"
	},
	{
		"id": "5047",
		"name": "Joy Lemon 250ml",
		"price": 100.00,
		"category": "general-merchandise",
		"subcategory": "Kitchen Cleaning Materials",
		"brand": "Joy",
		"tags": ["dishwashing","joy","lemon","kitchen"],
		"stock": 5,
		"description": "Joy Lemon 250ml",
		"image_url": "images/general-merch/kitchen/joy-lemon-250ml.jpg",
		"image_webp": "images/general-merch/kitchen/joy-lemon-250ml.webp"
	},
	{
		"id": "5048",
		"name": "Joy Lemon 40ml",
		"price": 20.00,
		"category": "general-merchandise",
		"subcategory": "Kitchen Cleaning Materials",
		"brand": "Joy",
		"tags": ["dishwashing","joy","lemon","sachet","kitchen"],
		"stock": 10,
		"description": "Joy Lemon 40ml",
		"image_url": "images/general-merch/kitchen/joy-lemon-40ml.jpg",
		"image_webp": "images/general-merch/kitchen/joy-lemon-40ml.webp"
	},
	{
		"id": "5049",
		"name": "Smart Dishwashing Paste Calamansi 400g",
		"price": 100.00,
		"category": "general-merchandise",
		"subcategory": "Kitchen Cleaning Materials",
		"brand": "Smart",
		"tags": ["dishwashing","paste","smart","calamansi","kitchen"],
		"stock": 5,
		"description": "Smart Dishwashing Paste Calamansi 400g",
		"image_url": "images/general-merch/kitchen/smart-dishwashing-paste-calamansi-400g.jpg",
		"image_webp": "images/general-merch/kitchen/smart-dishwashing-paste-calamansi-400g.webp"
	},
	{
		"id": "5050",
		"name": "Smart Dishwashing Paste Calamansi 200g",
		"price": 50.00,
		"category": "general-merchandise",
		"subcategory": "Kitchen Cleaning Materials",
		"brand": "Smart",
		"tags": ["dishwashing","paste","smart","calamansi","kitchen"],
		"stock": 10,
		"description": "Smart Dishwashing Paste Calamansi 200g",
		"image_url": "images/general-merch/kitchen/smart-dishwashing-paste-calamansi-200g.jpg",
		"image_webp": "images/general-merch/kitchen/smart-dishwashing-paste-calamansi-200g.webp"
	},
	{
		"id": "5051",
		"name": "Smart Dishwashing Paste Lemon 400g",
		"price": 100.00,
		"category": "general-merchandise",
		"subcategory": "Kitchen Cleaning Materials",
		"brand": "Smart",
		"tags": ["dishwashing","paste","smart","lemon","kitchen"],
		"stock": 5,
		"description": "Smart Dishwashing Paste Lemon 400g",
		"image_url": "images/general-merch/kitchen/smart-dishwashing-paste-lemon-400g.jpg",
		"image_webp": "images/general-merch/kitchen/smart-dishwashing-paste-lemon-400g.webp"
	},
	{
		"id": "5052",
		"name": "Smart Dishwashing Paste Lemon 200g",
		"price": 50.00,
		"category": "general-merchandise",
		"subcategory": "Kitchen Cleaning Materials",
		"brand": "Smart",
		"tags": ["dishwashing","paste","smart","lemon","kitchen"],
		"stock": 10,
		"description": "Smart Dishwashing Paste Lemon 200g",
		"image_url": "images/general-merch/kitchen/smart-dishwashing-paste-lemon-200g.jpg",
		"image_webp": "images/general-merch/kitchen/smart-dishwashing-paste-lemon-200g.webp"
	},
	{
		"id": "5053",
		"name": "Scotch Brite 100mm x 75mm x 30mm",
		"price": 40.00,
		"category": "general-merchandise",
		"subcategory": "Kitchen Cleaning Materials",
		"brand": "Scotch-Brite",
		"tags": ["scotch-brite","sponge","kitchen","scouring"],
		"stock": 10,
		"description": "Scotch Brite 100mm x 75mm x 30mm",
		"image_url": "images/general-merch/kitchen/scotch-brite-100x75x30mm.jpg",
		"image_webp": "images/general-merch/kitchen/scotch-brite-100x75x30mm.webp"
	},
	{
		"id": "5054",
		"name": "Steel Wool",
		"price": 30.00,
		"category": "general-merchandise",
		"subcategory": "Kitchen Cleaning Materials",
		"brand": "Steel Wool",
		"tags": ["scouring","steel-wool","kitchen"],
		"stock": 10,
		"description": "Steel Wool",
		"image_url": "images/general-merch/kitchen/steel-wool.jpg",
		"image_webp": "images/general-merch/kitchen/steel-wool.webp"
	}
]
